complexity_diffusion/__init__.py
complexity_diffusion/core/__init__.py
complexity_diffusion/core/dynamics.py
complexity_diffusion/core/normalization.py
complexity_diffusion/cuda/__init__.py
complexity_diffusion/cuda/triton_attention.py
complexity_diffusion/cuda/triton_dynamics.py
complexity_diffusion/cuda/triton_norm.py
complexity_diffusion/dit/__init__.py
complexity_diffusion/dit/complexity_dit.py
complexity_diffusion/pipeline/__init__.py
complexity_diffusion/pipeline/text_to_image.py
complexity_diffusion/vae/__init__.py
complexity_diffusion/vae/complexity_vae.py
complexity_diffusion-0.3.0.dist-info/METADATA
complexity_diffusion-0.3.0.dist-info/WHEEL
complexity_diffusion-0.3.0.dist-info/top_level.txt
complexity_diffusion-0.3.0.dist-info/RECORD
