Metadata-Version: 2.4
Name: complexity-diffusion
Version: 0.3.0
Summary: Mu-Guided DiT with INL Dynamics for image generation
Home-page: https://github.com/Web3-League/complexity-diffusion
Author: Pacific Prime
Author-email: contact@pacific-prime.ai
Keywords: diffusion transformer llama inl-dynamics image-generation pytorch
Classifier: Development Status :: 3 - Alpha
Classifier: Intended Audience :: Developers
Classifier: Intended Audience :: Science/Research
Classifier: License :: OSI Approved :: MIT License
Classifier: Operating System :: OS Independent
Classifier: Programming Language :: Python :: 3
Classifier: Programming Language :: Python :: 3.8
Classifier: Programming Language :: Python :: 3.9
Classifier: Programming Language :: Python :: 3.10
Classifier: Programming Language :: Python :: 3.11
Classifier: Topic :: Scientific/Engineering :: Artificial Intelligence
Classifier: Topic :: Scientific/Engineering :: Image Recognition
Requires-Python: >=3.8
Requires-Dist: torch>=2.0.0
Requires-Dist: torchvision>=0.15.0
Requires-Dist: tqdm>=4.66.0
Requires-Dist: pillow>=9.0.0
Requires-Dist: numpy>=1.21.0
Provides-Extra: train
Requires-Dist: datasets>=2.16.0; extra == "train"
Requires-Dist: tensorboard>=2.15.0; extra == "train"
Requires-Dist: wandb>=0.16.0; extra == "train"
Requires-Dist: accelerate>=0.25.0; extra == "train"
Provides-Extra: cuda
Requires-Dist: triton>=2.0.0; extra == "cuda"
Provides-Extra: dev
Requires-Dist: pytest>=7.0.0; extra == "dev"
Requires-Dist: black>=23.0.0; extra == "dev"
Requires-Dist: isort>=5.12.0; extra == "dev"
Dynamic: author
Dynamic: author-email
Dynamic: classifier
Dynamic: description
Dynamic: description-content-type
Dynamic: home-page
Dynamic: keywords
Dynamic: provides-extra
Dynamic: requires-dist
Dynamic: requires-python
Dynamic: summary
